{
  "date": "2026-05-17",
  "posts": [
    {
      "time": "00:00",
      "timestamp": "2026-05-17T00:00:44.797178",
      "items": [
        {
          "headline": "UBS預計霍爾木茲海峽若持續關閉，全球石油庫存恐於五月底前跌至歷史新低。這將直接推升能源價格，對全球通膨構成巨大威脅，並可能引發經濟下行風險。",
          "impact": "建議增持能源類股及抗通膨資產，減持對高油價敏感的運輸及製造業股票，並關注避險商品黃金。"
        },
        {
          "headline": "能源地緣政治專家Daleep Singh警告，債券市場正對伊朗局勢閃爍警訊，暗示未來可能出現能源市場動盪與供應中斷風險。這凸顯了中東不穩定性對全球經濟的深遠影響。",
          "impact": "增持黃金及美國國債等避險資產，同時審慎評估與中東原油供應鏈相關的投資風險。"
        },
        {
          "headline": "川普聲稱習近平同意伊朗必須重開霍爾木茲海峽，但中方尚無明確表態介入。此言論若屬實，顯示國際社會對該戰略要道的通行高度關切，有助緩解部分地緣政治緊張。",
          "impact": "短期內對油價及全球航運市場影響不明，建議保持觀望，避免過度追高或殺低，並關注後續外交進展。"
        }
      ]
    }
  ],
  "total": 1
}