{"symbol":"NEWT","date":"2026-04-07","bars_available":1566,"tradingview_rating":{"summary":{"signal":"Neutral","score":0.0,"buy":8,"sell":8,"neutral":10},"oscillators":{"signal":"Neutral","score":0.0,"buy":1,"sell":1,"neutral":9,"details":{"RSI(14)":{"value":43.2,"signal":0},"Stoch(14,3,3)":{"value":null,"signal":0},"CCI(20)":{"value":13.4,"signal":0},"ADX(14)":{"value":null,"signal":0},"AO":{"value":-0.75,"signal":0},"Momentum(10)":{"value":0.05,"signal":-1},"MACD(12,26,9)":{"value":null,"signal":0},"StochRSI(3,3,14,14)":{"value":null,"signal":0},"W%R(14)":{"value":-30.9,"signal":0},"BBP(13)":{"value":0.37,"signal":1},"UO(7,14,28)":{"value":56.9,"signal":0}}},"moving_averages":{"signal":"Neutral","score":0.0,"buy":7,"sell":7,"neutral":1,"details":{"SMA(10)":{"value":11.06,"signal":1},"SMA(20)":{"value":11.41,"signal":1},"SMA(30)":{"value":11.76,"signal":-1},"SMA(50)":{"value":12.44,"signal":-1},"SMA(100)":{"value":11.75,"signal":-1},"SMA(200)":{"value":11.43,"signal":1},"EMA(10)":{"value":11.25,"signal":1},"EMA(20)":{"value":11.45,"signal":1},"EMA(30)":{"value":11.66,"signal":-1},"EMA(50)":{"value":11.86,"signal":-1},"EMA(100)":{"value":11.82,"signal":-1},"EMA(200)":{"value":11.61,"signal":-1},"HMA(9)":{"value":11.48,"signal":1},"VWMA(20)":{"value":11.34,"signal":1},"Ichimoku(9,26,52)":{"value":12.65,"signal":0}}}},"extended_rating":{"summary":{"signal":"Neutral","score":-0.01,"buy":21,"sell":22,"neutral":60},"categories":{"trend":{"signal":"Strong Sell","score":-0.67,"buy":1,"sell":7,"neutral":1},"momentum":{"signal":"Sell","score":-0.2,"buy":2,"sell":3,"neutral":0},"volatility":{"signal":"Neutral","score":0.0,"buy":1,"sell":1,"neutral":14},"volume":{"signal":"Buy","score":0.5,"buy":6,"sell":1,"neutral":3},"pattern":{"signal":"Neutral","score":0.04,"buy":2,"sell":1,"neutral":24},"support_resistance":{"signal":"Neutral","score":-0.05,"buy":5,"sell":6,"neutral":8},"relative":{"signal":"Strong Buy","score":0.67,"buy":4,"sell":0,"neutral":2},"statistical":{"signal":"Sell","score":-0.29,"buy":0,"sell":2,"neutral":5},"time_based":{"signal":"Sell","score":-0.25,"buy":0,"sell":1,"neutral":3}}},"chart_patterns":[{"name":"盤整震盪","type":"trend","direction":"Neutral","reliability":"趨勢判定 (20日 -4.9%, 50日 -17.7%)","description":"近 20 日漲跌 -4.9%，均線糾結，無明確方向。價格在 MA20 ($11.41) 和 MA50 ($12.44) 之間來回。","current_status":"收盤 $11.52 | MA20 $11.41 | MA50 $12.44 | 均線糾結","price_target":null,"target_logic":"上方壓力 MA20 = $11.41，下方支撐 MA50 = $12.44","prediction":"等待方向。突破 MA20 ($11.41) 看多，跌破 MA50 ($12.44) 看空。量能放大時關注突破方向。","key_levels":{"ma20":11.41,"ma50":12.44,"current":11.52}}],"indicators":{"trend":{"parabolic_sar":{"value":10.42,"signal":"Buy"},"supertrend":{"value":11.72,"signal":"Sell"},"aroon_up":{"value":12.0,"signal":"Sell"},"aroon_down":{"value":80.0,"signal":"Sell"},"aroon_osc":{"value":-68.0,"signal":"Sell"},"vortex_plus":{"value":0.883,"signal":"Sell"},"vortex_minus":{"value":0.978,"signal":"Sell"},"lr_slope":{"value":-0.0553,"signal":"Sell"},"r_squared":{"value":0.482,"signal":"Normal"}},"momentum":{"roc_14":{"value":-3.84,"signal":"Sell"},"tsi":{"value":0.0,"signal":"Sell"},"coppock":{"value":-11.73,"signal":"Sell"},"ppo":{"value":-2.72,"signal":"Buy"},"dpo":{"value":0.06,"signal":"Buy"}},"volatility":{"atr_14":{"value":0.4,"signal":"Normal"},"atr_pct":{"value":3.46,"signal":"Normal"},"bb_upper":{"value":12.33,"signal":"Neutral"},"bb_middle":{"value":11.41,"signal":"Buy"},"bb_lower":{"value":10.49,"signal":"Neutral"},"bb_width":{"value":16.11,"signal":"Normal"},"bb_pctb":{"value":0.56,"signal":"Neutral"},"keltner_upper":{"value":12.21,"signal":"Neutral"},"keltner_lower":{"value":10.7,"signal":"Neutral"},"donchian_high":{"value":12.43,"signal":"Neutral"},"donchian_low":{"value":10.4,"signal":"Neutral"},"hv_20":{"value":36.8,"signal":"Normal"},"stddev_20":{"value":0.46,"signal":"Normal"},"chaikin_vol":{"value":-2.1,"signal":"Falling"},"mass_index":{"value":25.0,"signal":"Normal"},"ulcer_index":{"value":6.6,"signal":"Normal"}},"volume":{"volume":{"value":216611,"signal":"Normal"},"obv":{"value":4078942,"signal":"Buy"},"ad_line":{"value":-11198236,"signal":"Buy"},"cmf_20":{"value":-0.013,"signal":"Neutral"},"mfi_14":{"value":45.6,"signal":"Neutral"},"vpt":{"value":-1843802,"signal":"Buy"},"force_index":{"value":9321.0,"signal":"Buy"},"vol_osc":{"value":12.5,"signal":"Buy"},"nvi":{"value":1339.4,"signal":"Sell"},"pvi":{"value":643.5,"signal":"Buy"}},"pattern":{"close_position":{"value":80.0,"signal":"Buy"},"body_ratio":{"value":6.7,"signal":"Weak"},"upper_shadow":{"value":13.3,"signal":"Neutral"},"lower_shadow":{"value":80.0,"signal":"Buy"},"gap_pct":{"value":-0.26,"signal":"Neutral"},"intraday_range":{"value":1.3,"signal":"Normal"},"doji":{"value":"True","signal":"Neutral"},"engulfing":{"value":"None","signal":"Neutral"},"hammer":{"value":"False","signal":"Neutral"},"inside_bar":{"value":"True","signal":"Neutral"},"outside_bar":{"value":"False","signal":"Neutral"},"morning_star":{"value":"False","signal":"Neutral"},"evening_star":{"value":"False","signal":"Neutral"},"pattern_name":{"value":"Doji","signal":"Neutral"},"chart_pattern":{"value":"盤整震盪","signal":"Neutral"},"head_shoulders":{"value":false,"signal":"Neutral"},"inv_head_shoulders":{"value":false,"signal":"Neutral"},"double_top":{"value":false,"signal":"Neutral"},"double_bottom":{"value":false,"signal":"Neutral"},"sym_triangle":{"value":false,"signal":"Neutral"},"asc_triangle":{"value":false,"signal":"Neutral"},"desc_triangle":{"value":false,"signal":"Neutral"},"rising_wedge":{"value":false,"signal":"Neutral"},"falling_wedge":{"value":false,"signal":"Neutral"},"bull_flag":{"value":false,"signal":"Neutral"},"bear_flag":{"value":false,"signal":"Neutral"},"cup_handle":{"value":false,"signal":"Neutral"}},"support_resistance":{"pivot":{"value":11.49,"signal":"Buy"},"r1":{"value":11.58,"signal":"Near"},"s1":{"value":11.43,"signal":"Near"},"r2":{"value":11.64,"signal":"Neutral"},"s2":{"value":11.34,"signal":"Neutral"},"r3":{"value":11.73,"signal":"Neutral"},"s3":{"value":11.28,"signal":"Neutral"},"high_52wk":{"value":14.91,"signal":"Neutral"},"low_52wk":{"value":8.52,"signal":"Neutral"},"ath":{"value":26.17,"signal":"Neutral"},"ath_dist":{"value":44.0,"signal":"Far"},"fib_0":{"value":10.4,"signal":"Support"},"fib_236":{"value":11.46,"signal":"Near"},"fib_382":{"value":12.12,"signal":"Resistance"},"fib_500":{"value":12.65,"signal":"Resistance"},"fib_618":{"value":13.19,"signal":"Resistance"},"fib_786":{"value":13.94,"signal":"Resistance"},"fib_100":{"value":14.91,"signal":"Resistance"},"vpoc":{"value":11.55,"signal":"Resistance"}},"relative":{"rs_line":{"value":0.0175,"signal":"Buy"},"rs_line_trend":{"value":"Rising","signal":"Buy"},"beta_60":{"value":1.03,"signal":"Normal"},"correlation_spy":{"value":0.38,"signal":"Normal"},"alpha_60":{"value":24.2,"signal":"Buy"},"info_ratio":{"value":0.64,"signal":"Buy"}},"statistical":{"sharpe_60":{"value":0.27,"signal":"Neutral"},"sortino_60":{"value":0.24,"signal":"Neutral"},"mdd_60":{"value":-28.6,"signal":"High Risk"},"skewness":{"value":-0.25,"signal":"Neutral"},"kurtosis":{"value":0.81,"signal":"Normal"},"var_95":{"value":-4.74,"signal":"Normal"},"cvar_95":{"value":-5.96,"signal":"High Risk"}},"time_based":{"consec_up":{"value":0,"signal":"Neutral"},"consec_down":{"value":1,"signal":"Neutral"},"day_of_week":{"value":"Tue","signal":"Neutral"},"days_since_high":{"value":1207,"signal":"Sell"}}},"validation":{"checks":122,"passed":122,"errors":0,"warnings":0,"status":"PASS","error_list":[],"warning_list":[],"indicator_count":103,"empty_signals":0}}