{"symbol":"OCUL","date":"2026-05-11","bars_available":1593,"tradingview_rating":{"summary":{"signal":"Sell","score":-0.35,"buy":3,"sell":12,"neutral":11},"oscillators":{"signal":"Neutral","score":-0.09,"buy":0,"sell":1,"neutral":10,"details":{"RSI(14)":{"value":36.5,"signal":0},"Stoch(14,3,3)":{"value":null,"signal":0},"CCI(20)":{"value":10.7,"signal":0},"ADX(14)":{"value":null,"signal":0},"AO":{"value":0.71,"signal":0},"Momentum(10)":{"value":-0.21,"signal":-1},"MACD(12,26,9)":{"value":null,"signal":0},"StochRSI(3,3,14,14)":{"value":null,"signal":0},"W%R(14)":{"value":-76.0,"signal":0},"BBP(13)":{"value":0.01,"signal":0},"UO(7,14,28)":{"value":58.1,"signal":0}}},"moving_averages":{"signal":"Strong Sell","score":-0.53,"buy":3,"sell":11,"neutral":1,"details":{"SMA(10)":{"value":9.5,"signal":-1},"SMA(20)":{"value":9.36,"signal":-1},"SMA(30)":{"value":8.99,"signal":1},"SMA(50)":{"value":9.1,"signal":1},"SMA(100)":{"value":9.96,"signal":-1},"SMA(200)":{"value":11.01,"signal":-1},"EMA(10)":{"value":9.49,"signal":-1},"EMA(20)":{"value":9.34,"signal":-1},"EMA(30)":{"value":9.24,"signal":1},"EMA(50)":{"value":9.28,"signal":-1},"EMA(100)":{"value":9.71,"signal":-1},"EMA(200)":{"value":10.02,"signal":-1},"HMA(9)":{"value":9.66,"signal":-1},"VWMA(20)":{"value":9.4,"signal":-1},"Ichimoku(9,26,52)":{"value":9.44,"signal":0}}}},"extended_rating":{"summary":{"signal":"Neutral","score":-0.01,"buy":23,"sell":24,"neutral":56},"categories":{"trend":{"signal":"Strong Buy","score":0.89,"buy":8,"sell":0,"neutral":1},"momentum":{"signal":"Sell","score":-0.2,"buy":2,"sell":3,"neutral":0},"volatility":{"signal":"Neutral","score":0.06,"buy":2,"sell":1,"neutral":13},"volume":{"signal":"Neutral","score":0.0,"buy":4,"sell":4,"neutral":2},"pattern":{"signal":"Neutral","score":-0.04,"buy":1,"sell":2,"neutral":24},"support_resistance":{"signal":"Sell","score":-0.16,"buy":3,"sell":6,"neutral":10},"relative":{"signal":"Sell","score":-0.17,"buy":2,"sell":3,"neutral":1},"statistical":{"signal":"Sell","score":-0.43,"buy":1,"sell":4,"neutral":2},"time_based":{"signal":"Sell","score":-0.25,"buy":0,"sell":1,"neutral":3}}},"chart_patterns":[{"name":"對稱三角 Symmetrical Triangle","type":"continuation","direction":"Neutral","reliability":"中 (方向不確定，等突破確認)","description":"高點逐步降低、低點逐步升高，形成三角收斂。壓力 $9.95 / 支撐 $9.06。價格波動幅度從 $4.12 收窄至 $0.89。","current_status":"價格在三角形內收斂，即將突破","price_target":10.84,"target_logic":"突破方向 ± 三角形高度 $0.89","prediction":"中性等待。向上突破 $9.95 → 看多目標 $10.84；向下跌破 $9.06 → 看空目標 $8.17。通常在三角形 2/3 處突破。","key_levels":{"resistance":9.95,"support":9.06,"up_target":10.84,"down_target":8.17}}],"indicators":{"trend":{"parabolic_sar":{"value":9.1,"signal":"Buy"},"supertrend":{"value":8.48,"signal":"Buy"},"aroon_up":{"value":92.0,"signal":"Buy"},"aroon_down":{"value":12.0,"signal":"Buy"},"aroon_osc":{"value":80.0,"signal":"Buy"},"vortex_plus":{"value":1.017,"signal":"Buy"},"vortex_minus":{"value":1.01,"signal":"Buy"},"lr_slope":{"value":0.0378,"signal":"Buy"},"r_squared":{"value":0.403,"signal":"Normal"}},"momentum":{"roc_14":{"value":-5.5,"signal":"Sell"},"tsi":{"value":0.0,"signal":"Sell"},"coppock":{"value":8.53,"signal":"Buy"},"ppo":{"value":2.08,"signal":"Sell"},"dpo":{"value":0.13,"signal":"Buy"}},"volatility":{"atr_14":{"value":0.42,"signal":"Normal"},"atr_pct":{"value":4.52,"signal":"Normal"},"bb_upper":{"value":10.05,"signal":"Neutral"},"bb_middle":{"value":9.36,"signal":"Sell"},"bb_lower":{"value":8.68,"signal":"Neutral"},"bb_width":{"value":14.68,"signal":"Normal"},"bb_pctb":{"value":0.44,"signal":"Neutral"},"keltner_upper":{"value":10.24,"signal":"Neutral"},"keltner_lower":{"value":8.44,"signal":"Neutral"},"donchian_high":{"value":9.98,"signal":"Neutral"},"donchian_low":{"value":8.5,"signal":"Neutral"},"hv_20":{"value":49.7,"signal":"Normal"},"stddev_20":{"value":0.34,"signal":"Normal"},"chaikin_vol":{"value":7.3,"signal":"Rising"},"mass_index":{"value":25.0,"signal":"Normal"},"ulcer_index":{"value":2.41,"signal":"Low Risk"}},"volume":{"volume":{"value":3416428,"signal":"Normal"},"obv":{"value":22107414,"signal":"Sell"},"ad_line":{"value":-39875688,"signal":"Buy"},"cmf_20":{"value":0.106,"signal":"Buy"},"mfi_14":{"value":42.8,"signal":"Neutral"},"vpt":{"value":23582733,"signal":"Sell"},"force_index":{"value":-54015.0,"signal":"Sell"},"vol_osc":{"value":13.0,"signal":"Buy"},"nvi":{"value":55.7,"signal":"Sell"},"pvi":{"value":42190.4,"signal":"Buy"}},"pattern":{"close_position":{"value":18.2,"signal":"Sell"},"body_ratio":{"value":70.9,"signal":"Strong"},"upper_shadow":{"value":10.9,"signal":"Neutral"},"lower_shadow":{"value":18.2,"signal":"Neutral"},"gap_pct":{"value":-0.1,"signal":"Neutral"},"intraday_range":{"value":5.69,"signal":"High"},"doji":{"value":"False","signal":"Neutral"},"engulfing":{"value":"None","signal":"Neutral"},"hammer":{"value":"False","signal":"Neutral"},"inside_bar":{"value":"False","signal":"Neutral"},"outside_bar":{"value":"False","signal":"Neutral"},"morning_star":{"value":"False","signal":"Neutral"},"evening_star":{"value":"False","signal":"Neutral"},"pattern_name":{"value":"None","signal":"Neutral"},"sym_triangle":{"value":true,"signal":"Neutral"},"chart_pattern":{"value":"對稱三角 Symmetrical Triangle","signal":"Neutral"},"head_shoulders":{"value":false,"signal":"Neutral"},"inv_head_shoulders":{"value":false,"signal":"Neutral"},"double_top":{"value":false,"signal":"Neutral"},"double_bottom":{"value":false,"signal":"Neutral"},"asc_triangle":{"value":false,"signal":"Neutral"},"desc_triangle":{"value":false,"signal":"Neutral"},"rising_wedge":{"value":false,"signal":"Neutral"},"falling_wedge":{"value":false,"signal":"Neutral"},"bull_flag":{"value":false,"signal":"Neutral"},"bear_flag":{"value":false,"signal":"Neutral"},"cup_handle":{"value":false,"signal":"Neutral"}},"support_resistance":{"pivot":{"value":9.4,"signal":"Sell"},"r1":{"value":9.61,"signal":"Neutral"},"s1":{"value":9.06,"signal":"Neutral"},"r2":{"value":9.95,"signal":"Neutral"},"s2":{"value":8.85,"signal":"Neutral"},"r3":{"value":10.16,"signal":"Neutral"},"s3":{"value":8.51,"signal":"Neutral"},"high_52wk":{"value":16.44,"signal":"Neutral"},"low_52wk":{"value":6.23,"signal":"Neutral"},"ath":{"value":24.3,"signal":"Neutral"},"ath_dist":{"value":38.2,"signal":"Far"},"fib_0":{"value":7.38,"signal":"Support"},"fib_236":{"value":8.35,"signal":"Support"},"fib_382":{"value":8.95,"signal":"Support"},"fib_500":{"value":9.44,"signal":"Resistance"},"fib_618":{"value":9.93,"signal":"Resistance"},"fib_786":{"value":10.62,"signal":"Resistance"},"fib_100":{"value":11.5,"signal":"Resistance"},"vpoc":{"value":9.66,"signal":"Resistance"}},"relative":{"rs_line":{"value":0.0126,"signal":"Sell"},"rs_line_trend":{"value":"Falling","signal":"Sell"},"beta_60":{"value":1.74,"signal":"High"},"correlation_spy":{"value":0.28,"signal":"Low"},"alpha_60":{"value":4.1,"signal":"Buy"},"info_ratio":{"value":0.28,"signal":"Neutral"}},"statistical":{"sharpe_60":{"value":0.58,"signal":"Neutral"},"sortino_60":{"value":0.73,"signal":"Neutral"},"mdd_60":{"value":-33.0,"signal":"High Risk"},"skewness":{"value":0.6,"signal":"Buy"},"kurtosis":{"value":5.04,"signal":"High Risk"},"var_95":{"value":-6.43,"signal":"High Risk"},"cvar_95":{"value":-11.45,"signal":"High Risk"}},"time_based":{"consec_up":{"value":0,"signal":"Neutral"},"consec_down":{"value":2,"signal":"Neutral"},"day_of_week":{"value":"Mon","signal":"Neutral"},"days_since_high":{"value":1351,"signal":"Sell"}}},"validation":{"checks":123,"passed":123,"errors":0,"warnings":0,"status":"PASS","error_list":[],"warning_list":[],"indicator_count":103,"empty_signals":0}}