{"symbol":"SILJ","date":"2026-04-01","bars_available":1563,"tradingview_rating":{"summary":{"signal":"Buy","score":0.19,"buy":11,"sell":6,"neutral":9},"oscillators":{"signal":"Buy","score":0.18,"buy":2,"sell":0,"neutral":9,"details":{"RSI(14)":{"value":40.2,"signal":0},"Stoch(14,3,3)":{"value":null,"signal":0},"CCI(20)":{"value":-3.1,"signal":0},"ADX(14)":{"value":null,"signal":0},"AO":{"value":-4.45,"signal":0},"Momentum(10)":{"value":-0.72,"signal":1},"MACD(12,26,9)":{"value":null,"signal":0},"StochRSI(3,3,14,14)":{"value":null,"signal":0},"W%R(14)":{"value":-41.9,"signal":0},"BBP(13)":{"value":2.39,"signal":1},"UO(7,14,28)":{"value":50.8,"signal":0}}},"moving_averages":{"signal":"Buy","score":0.2,"buy":9,"sell":6,"neutral":0,"details":{"SMA(10)":{"value":28.23,"signal":1},"SMA(20)":{"value":30.98,"signal":-1},"SMA(30)":{"value":33.0,"signal":-1},"SMA(50)":{"value":33.49,"signal":-1},"SMA(100)":{"value":29.25,"signal":1},"SMA(200)":{"value":23.59,"signal":1},"EMA(10)":{"value":29.3,"signal":1},"EMA(20)":{"value":30.57,"signal":1},"EMA(30)":{"value":31.31,"signal":-1},"EMA(50)":{"value":31.42,"signal":-1},"EMA(100)":{"value":29.35,"signal":1},"EMA(200)":{"value":25.07,"signal":1},"HMA(9)":{"value":29.29,"signal":1},"VWMA(20)":{"value":30.67,"signal":1},"Ichimoku(9,26,52)":{"value":33.45,"signal":-1}}}},"extended_rating":{"summary":{"signal":"Sell","score":-0.18,"buy":16,"sell":32,"neutral":42},"categories":{"trend":{"signal":"Strong Sell","score":-0.56,"buy":1,"sell":6,"neutral":2},"momentum":{"signal":"Strong Sell","score":-0.6,"buy":1,"sell":4,"neutral":0},"volatility":{"signal":"Sell","score":-0.5,"buy":0,"sell":8,"neutral":8},"volume":{"signal":"Buy","score":0.5,"buy":6,"sell":1,"neutral":3},"pattern":{"signal":"Neutral","score":-0.07,"buy":1,"sell":2,"neutral":11},"support_resistance":{"signal":"Sell","score":-0.26,"buy":2,"sell":7,"neutral":10},"relative":{"signal":"Strong Buy","score":0.83,"buy":5,"sell":0,"neutral":1},"statistical":{"signal":"Strong Sell","score":-0.57,"buy":0,"sell":4,"neutral":3},"time_based":{"signal":"Neutral","score":0.0,"buy":0,"sell":0,"neutral":4}}},"indicators":{"trend":{"parabolic_sar":{"value":25.81,"signal":"Buy"},"supertrend":{"value":32.78,"signal":"Sell"},"aroon_up":{"value":12.0,"signal":"Sell"},"aroon_down":{"value":68.0,"signal":"Neutral"},"aroon_osc":{"value":-56.0,"signal":"Sell"},"vortex_plus":{"value":0.901,"signal":"Sell"},"vortex_minus":{"value":0.957,"signal":"Sell"},"lr_slope":{"value":-0.4502,"signal":"Sell"},"r_squared":{"value":0.688,"signal":"Normal"}},"momentum":{"roc_14":{"value":-10.31,"signal":"Sell"},"tsi":{"value":0.0,"signal":"Sell"},"coppock":{"value":-33.72,"signal":"Sell"},"ppo":{"value":-4.96,"signal":"Sell"},"dpo":{"value":0.55,"signal":"Buy"}},"volatility":{"atr_14":{"value":1.92,"signal":"High"},"atr_pct":{"value":6.23,"signal":"High"},"bb_upper":{"value":37.24,"signal":""},"bb_middle":{"value":30.98,"signal":"Sell"},"bb_lower":{"value":24.72,"signal":""},"bb_width":{"value":40.4,"signal":"Expansion"},"bb_pctb":{"value":0.487,"signal":"Neutral"},"keltner_upper":{"value":34.64,"signal":""},"keltner_lower":{"value":26.49,"signal":""},"donchian_high":{"value":37.17,"signal":""},"donchian_low":{"value":25.81,"signal":""},"hv_20":{"value":75.2,"signal":"High"},"stddev_20":{"value":3.13,"signal":"High"},"chaikin_vol":{"value":-0.2,"signal":"Falling"},"mass_index":{"value":25.0,"signal":"Normal"},"ulcer_index":{"value":13.7,"signal":"High Risk"}},"volume":{"volume":{"value":6598556,"signal":"Normal"},"obv":{"value":246964604,"signal":"Buy"},"ad_line":{"value":205703415,"signal":"Buy"},"cmf_20":{"value":-0.042,"signal":"Neutral"},"mfi_14":{"value":56.9,"signal":"Neutral"},"vpt":{"value":7404044,"signal":"Buy"},"force_index":{"value":1439937.0,"signal":"Buy"},"vol_osc":{"value":6.7,"signal":"Buy"},"nvi":{"value":1045.0,"signal":"Buy"},"pvi":{"value":2654.9,"signal":"Sell"}},"pattern":{"close_position":{"value":45.7,"signal":"Neutral"},"body_ratio":{"value":8.6,"signal":"Weak"},"upper_shadow":{"value":54.3,"signal":"Sell"},"lower_shadow":{"value":37.1,"signal":""},"gap_pct":{"value":3.23,"signal":"Buy"},"intraday_range":{"value":4.92,"signal":"Normal"},"doji":{"value":"True","signal":"Neutral"},"engulfing":{"value":"None","signal":""},"hammer":{"value":"False","signal":""},"inside_bar":{"value":"False","signal":""},"outside_bar":{"value":"False","signal":""},"morning_star":{"value":"False","signal":""},"evening_star":{"value":"False","signal":""},"pattern_name":{"value":"Doji","signal":""}},"support_resistance":{"pivot":{"value":30.85,"signal":"Sell"},"r1":{"value":31.59,"signal":""},"s1":{"value":30.08,"signal":""},"r2":{"value":32.36,"signal":""},"s2":{"value":29.34,"signal":""},"r3":{"value":33.1,"signal":""},"s3":{"value":28.57,"signal":""},"high_52wk":{"value":41.1,"signal":""},"low_52wk":{"value":9.83,"signal":""},"ath":{"value":41.1,"signal":""},"ath_dist":{"value":75.0,"signal":""},"fib_0":{"value":25.81,"signal":"Support"},"fib_236":{"value":29.41,"signal":"Support"},"fib_382":{"value":31.65,"signal":"Resistance"},"fib_500":{"value":33.45,"signal":"Resistance"},"fib_618":{"value":35.26,"signal":"Resistance"},"fib_786":{"value":37.83,"signal":"Resistance"},"fib_100":{"value":41.1,"signal":"Resistance"},"vpoc":{"value":33.96,"signal":"Resistance"}},"relative":{"rs_line":{"value":0.047,"signal":"Buy"},"rs_line_trend":{"value":"Rising","signal":"Buy"},"beta_60":{"value":0.91,"signal":"Normal"},"correlation_spy":{"value":0.18,"signal":"Low"},"alpha_60":{"value":70.8,"signal":"Buy"},"info_ratio":{"value":0.99,"signal":"Buy"}},"statistical":{"sharpe_60":{"value":0.7,"signal":"Neutral"},"sortino_60":{"value":0.62,"signal":"Neutral"},"mdd_60":{"value":-34.7,"signal":"High Risk"},"skewness":{"value":-0.75,"signal":"Sell"},"kurtosis":{"value":0.93,"signal":"Normal"},"var_95":{"value":-7.85,"signal":"High Risk"},"cvar_95":{"value":-12.01,"signal":"High Risk"}},"time_based":{"consec_up":{"value":2,"signal":"Neutral"},"consec_down":{"value":0,"signal":""},"day_of_week":{"value":"Wed","signal":"Neutral"},"days_since_high":{"value":22,"signal":"Neutral"}}}}