{"symbol":"SNEX","date":"2026-06-25","bars_available":1611,"tradingview_rating":{"summary":{"signal":"Buy","score":0.46,"buy":15,"sell":3,"neutral":8},"oscillators":{"signal":"Neutral","score":-0.09,"buy":1,"sell":2,"neutral":8,"details":{"RSI(14)":{"value":83.9,"signal":-1},"Stoch(14,3,3)":{"value":null,"signal":0},"CCI(20)":{"value":82.3,"signal":0},"ADX(14)":{"value":null,"signal":0},"AO":{"value":17.91,"signal":1},"Momentum(10)":{"value":12.58,"signal":-1},"MACD(12,26,9)":{"value":null,"signal":0},"StochRSI(3,3,14,14)":{"value":null,"signal":0},"W%R(14)":{"value":-14.2,"signal":0},"BBP(13)":{"value":11.88,"signal":0},"UO(7,14,28)":{"value":52.9,"signal":0}}},"moving_averages":{"signal":"Strong Buy","score":0.87,"buy":14,"sell":1,"neutral":0,"details":{"SMA(10)":{"value":134.99,"signal":1},"SMA(20)":{"value":124.58,"signal":1},"SMA(30)":{"value":121.31,"signal":1},"SMA(50)":{"value":114.26,"signal":1},"SMA(100)":{"value":109.91,"signal":1},"SMA(200)":{"value":102.71,"signal":1},"EMA(10)":{"value":133.43,"signal":1},"EMA(20)":{"value":127.45,"signal":1},"EMA(30)":{"value":123.12,"signal":1},"EMA(50)":{"value":117.59,"signal":1},"EMA(100)":{"value":110.82,"signal":1},"EMA(200)":{"value":103.33,"signal":1},"HMA(9)":{"value":138.6,"signal":-1},"VWMA(20)":{"value":128.4,"signal":1},"Ichimoku(9,26,52)":{"value":128.52,"signal":1}}}},"extended_rating":{"summary":{"signal":"Buy","score":0.33,"buy":43,"sell":9,"neutral":51},"categories":{"trend":{"signal":"Strong Buy","score":0.89,"buy":8,"sell":0,"neutral":1},"momentum":{"signal":"Strong Buy","score":0.6,"buy":4,"sell":1,"neutral":0},"volatility":{"signal":"Buy","score":0.12,"buy":3,"sell":1,"neutral":12},"volume":{"signal":"Buy","score":0.2,"buy":5,"sell":3,"neutral":2},"pattern":{"signal":"Buy","score":0.11,"buy":3,"sell":0,"neutral":24},"support_resistance":{"signal":"Buy","score":0.42,"buy":10,"sell":2,"neutral":7},"relative":{"signal":"Strong Buy","score":1.0,"buy":6,"sell":0,"neutral":0},"statistical":{"signal":"Buy","score":0.14,"buy":3,"sell":2,"neutral":2},"time_based":{"signal":"Buy","score":0.25,"buy":1,"sell":0,"neutral":3}}},"chart_patterns":[{"name":"杯柄型態 Cup & Handle","type":"continuation","direction":"Buy","reliability":"高 (William O'Neil 經典，成功率 ~65%)","description":"U 形回升（杯深 10.4%，回復 132.8%）+ 小幅回檔（柄深 4.4%）。杯底 $91.62，右緣 $135.73。","current_status":"杯柄形成中，關注突破右緣 $135.73","price_target":179.84,"target_logic":"目標 = 右緣 $135.73 + 杯深 = $179.84","prediction":"看多。突破 $135.73 後預期漲至 $179.84（漲幅 31.0%）。放量突破確認。停損在柄底 $129.74。","key_levels":{"cup_low":91.62,"rim":135.73,"handle_low":129.74,"target":179.84}}],"indicators":{"trend":{"parabolic_sar":{"value":130.05,"signal":"Buy"},"supertrend":{"value":120.01,"signal":"Buy"},"aroon_up":{"value":88.0,"signal":"Buy"},"aroon_down":{"value":44.0,"signal":"Neutral"},"aroon_osc":{"value":44.0,"signal":"Buy"},"vortex_plus":{"value":1.258,"signal":"Buy"},"vortex_minus":{"value":0.609,"signal":"Buy"},"lr_slope":{"value":1.7936,"signal":"Buy"},"r_squared":{"value":0.863,"signal":"Strong"}},"momentum":{"roc_14":{"value":25.86,"signal":"Buy"},"tsi":{"value":0.0,"signal":"Sell"},"coppock":{"value":42.6,"signal":"Buy"},"ppo":{"value":5.94,"signal":"Buy"},"dpo":{"value":0.12,"signal":"Buy"}},"volatility":{"atr_14":{"value":6.34,"signal":"Normal"},"atr_pct":{"value":4.62,"signal":"Normal"},"bb_upper":{"value":146.85,"signal":"Neutral"},"bb_middle":{"value":124.58,"signal":"Buy"},"bb_lower":{"value":102.31,"signal":"Neutral"},"bb_width":{"value":35.75,"signal":"Expansion"},"bb_pctb":{"value":0.785,"signal":"Neutral"},"keltner_upper":{"value":140.56,"signal":"Neutral"},"keltner_lower":{"value":114.33,"signal":"Neutral"},"donchian_high":{"value":141.96,"signal":"Neutral"},"donchian_low":{"value":105.23,"signal":"Neutral"},"hv_20":{"value":45.0,"signal":"Normal"},"stddev_20":{"value":11.13,"signal":"Normal"},"chaikin_vol":{"value":13.2,"signal":"Rising"},"mass_index":{"value":25.0,"signal":"Normal"},"ulcer_index":{"value":1.18,"signal":"Low Risk"}},"volume":{"volume":{"value":747667,"signal":"Normal"},"obv":{"value":53097601,"signal":"Sell"},"ad_line":{"value":27567710,"signal":"Sell"},"cmf_20":{"value":0.096,"signal":"Buy"},"mfi_14":{"value":67.7,"signal":"Neutral"},"vpt":{"value":719003,"signal":"Buy"},"force_index":{"value":1359180.0,"signal":"Buy"},"vol_osc":{"value":11.1,"signal":"Buy"},"nvi":{"value":1226.9,"signal":"Sell"},"pvi":{"value":5183.4,"signal":"Buy"}},"pattern":{"close_position":{"value":47.2,"signal":"Neutral"},"body_ratio":{"value":21.3,"signal":"Normal"},"upper_shadow":{"value":31.5,"signal":"Neutral"},"lower_shadow":{"value":47.2,"signal":"Neutral"},"gap_pct":{"value":1.4,"signal":"Buy"},"intraday_range":{"value":2.55,"signal":"Normal"},"doji":{"value":"False","signal":"Neutral"},"engulfing":{"value":"None","signal":"Neutral"},"hammer":{"value":"False","signal":"Neutral"},"inside_bar":{"value":"True","signal":"Neutral"},"outside_bar":{"value":"False","signal":"Neutral"},"morning_star":{"value":"False","signal":"Neutral"},"evening_star":{"value":"False","signal":"Neutral"},"pattern_name":{"value":"Inside Bar","signal":"Neutral"},"cup_handle":{"value":true,"signal":"Buy"},"chart_pattern":{"value":"杯柄型態 Cup & Handle","signal":"Buy"},"head_shoulders":{"value":false,"signal":"Neutral"},"inv_head_shoulders":{"value":false,"signal":"Neutral"},"double_top":{"value":false,"signal":"Neutral"},"double_bottom":{"value":false,"signal":"Neutral"},"sym_triangle":{"value":false,"signal":"Neutral"},"asc_triangle":{"value":false,"signal":"Neutral"},"desc_triangle":{"value":false,"signal":"Neutral"},"rising_wedge":{"value":false,"signal":"Neutral"},"falling_wedge":{"value":false,"signal":"Neutral"},"bull_flag":{"value":false,"signal":"Neutral"},"bear_flag":{"value":false,"signal":"Neutral"}},"support_resistance":{"pivot":{"value":137.35,"signal":"Sell"},"r1":{"value":139.07,"signal":"Neutral"},"s1":{"value":135.55,"signal":"Neutral"},"r2":{"value":140.87,"signal":"Neutral"},"s2":{"value":133.83,"signal":"Neutral"},"r3":{"value":142.59,"signal":"Neutral"},"s3":{"value":132.03,"signal":"Neutral"},"high_52wk":{"value":141.96,"signal":"Near"},"low_52wk":{"value":68.97,"signal":"Neutral"},"ath":{"value":141.96,"signal":"Near ATH"},"ath_dist":{"value":96.7,"signal":"Near ATH"},"fib_0":{"value":89.35,"signal":"Support"},"fib_236":{"value":101.77,"signal":"Support"},"fib_382":{"value":109.45,"signal":"Support"},"fib_500":{"value":115.66,"signal":"Support"},"fib_618":{"value":121.86,"signal":"Support"},"fib_786":{"value":130.7,"signal":"Support"},"fib_100":{"value":141.96,"signal":"Resistance"},"vpoc":{"value":131.15,"signal":"Support"}},"relative":{"rs_line":{"value":0.187,"signal":"Buy"},"rs_line_trend":{"value":"Rising","signal":"Buy"},"beta_60":{"value":0.39,"signal":"Low"},"correlation_spy":{"value":0.13,"signal":"Low"},"alpha_60":{"value":270.6,"signal":"Buy"},"info_ratio":{"value":5.08,"signal":"Buy"}},"statistical":{"sharpe_60":{"value":6.19,"signal":"Buy"},"sortino_60":{"value":8.38,"signal":"Buy"},"mdd_60":{"value":-11.8,"signal":"Normal"},"skewness":{"value":1.0,"signal":"Buy"},"kurtosis":{"value":4.43,"signal":"High Risk"},"var_95":{"value":-2.89,"signal":"Normal"},"cvar_95":{"value":-5.17,"signal":"High Risk"}},"time_based":{"consec_up":{"value":1,"signal":"Neutral"},"consec_down":{"value":0,"signal":"Neutral"},"day_of_week":{"value":"Thu","signal":"Neutral"},"days_since_high":{"value":4,"signal":"Buy"}}},"validation":{"checks":123,"passed":123,"errors":0,"warnings":0,"status":"PASS","error_list":[],"warning_list":[],"indicator_count":103,"empty_signals":0}}