{"symbol":"STN","date":"2026-06-11","bars_available":1597,"tradingview_rating":{"summary":{"signal":"Strong Sell","score":-0.54,"buy":3,"sell":17,"neutral":6},"oscillators":{"signal":"Neutral","score":0.09,"buy":3,"sell":2,"neutral":6,"details":{"RSI(14)":{"value":34.5,"signal":0},"Stoch(14,3,3)":{"value":null,"signal":0},"CCI(20)":{"value":-204.9,"signal":1},"ADX(14)":{"value":null,"signal":0},"AO":{"value":-7.91,"signal":-1},"Momentum(10)":{"value":-3.64,"signal":1},"MACD(12,26,9)":{"value":null,"signal":0},"StochRSI(3,3,14,14)":{"value":null,"signal":0},"W%R(14)":{"value":-82.9,"signal":1},"BBP(13)":{"value":-6.15,"signal":-1},"UO(7,14,28)":{"value":34.9,"signal":0}}},"moving_averages":{"signal":"Strong Sell","score":-1.0,"buy":0,"sell":15,"neutral":0,"details":{"SMA(10)":{"value":74.02,"signal":-1},"SMA(20)":{"value":75.0,"signal":-1},"SMA(30)":{"value":79.65,"signal":-1},"SMA(50)":{"value":83.05,"signal":-1},"SMA(100)":{"value":88.79,"signal":-1},"SMA(200)":{"value":97.7,"signal":-1},"EMA(10)":{"value":73.88,"signal":-1},"EMA(20)":{"value":76.22,"signal":-1},"EMA(30)":{"value":78.35,"signal":-1},"EMA(50)":{"value":81.68,"signal":-1},"EMA(100)":{"value":87.23,"signal":-1},"EMA(200)":{"value":91.77,"signal":-1},"HMA(9)":{"value":71.95,"signal":-1},"VWMA(20)":{"value":75.0,"signal":-1},"Ichimoku(9,26,52)":{"value":82.23,"signal":-1}}}},"extended_rating":{"summary":{"signal":"Sell","score":-0.32,"buy":9,"sell":42,"neutral":52},"categories":{"trend":{"signal":"Strong Sell","score":-0.89,"buy":0,"sell":8,"neutral":1},"momentum":{"signal":"Strong Sell","score":-0.6,"buy":1,"sell":4,"neutral":0},"volatility":{"signal":"Neutral","score":-0.06,"buy":2,"sell":3,"neutral":11},"volume":{"signal":"Strong Sell","score":-0.6,"buy":1,"sell":7,"neutral":2},"pattern":{"signal":"Neutral","score":-0.04,"buy":1,"sell":2,"neutral":24},"support_resistance":{"signal":"Sell","score":-0.16,"buy":4,"sell":7,"neutral":8},"relative":{"signal":"Strong Sell","score":-0.67,"buy":0,"sell":4,"neutral":2},"statistical":{"signal":"Strong Sell","score":-0.86,"buy":0,"sell":6,"neutral":1},"time_based":{"signal":"Sell","score":-0.25,"buy":0,"sell":1,"neutral":3}}},"chart_patterns":[{"name":"雙頂 Double Top (M 頭)","type":"reversal","direction":"Sell","reliability":"高 (經典看空反轉，成功率 ~65%)","description":"價格兩次觸及相近高點 $92.57 和 $93.62，形成 M 字型。跌破中間谷底 $88.29 確認反轉。","current_status":"已跌破谷底支撐 $88.29，型態確認","price_target":82.96,"target_logic":"目標價 = 谷底 $88.29 - (頂部 - 谷底) = $82.96","prediction":"看空。預期下跌至 $82.96（跌幅 -15.2%）。若反彈回 $88.29 以上則型態失效。","key_levels":{"top1":92.57,"top2":93.62,"valley":88.29,"target":82.96}}],"indicators":{"trend":{"parabolic_sar":{"value":78.59,"signal":"Sell"},"supertrend":{"value":77.91,"signal":"Sell"},"aroon_up":{"value":8.0,"signal":"Sell"},"aroon_down":{"value":100.0,"signal":"Sell"},"aroon_osc":{"value":-92.0,"signal":"Sell"},"vortex_plus":{"value":0.894,"signal":"Sell"},"vortex_minus":{"value":1.149,"signal":"Sell"},"lr_slope":{"value":-0.1946,"signal":"Sell"},"r_squared":{"value":0.429,"signal":"Normal"}},"momentum":{"roc_14":{"value":-5.45,"signal":"Sell"},"tsi":{"value":0.0,"signal":"Sell"},"coppock":{"value":-8.88,"signal":"Sell"},"ppo":{"value":-4.14,"signal":"Sell"},"dpo":{"value":0.66,"signal":"Buy"}},"volatility":{"atr_14":{"value":2.03,"signal":"Normal"},"atr_pct":{"value":2.83,"signal":"Normal"},"bb_upper":{"value":78.43,"signal":"Neutral"},"bb_middle":{"value":75.0,"signal":"Sell"},"bb_lower":{"value":71.58,"signal":"Neutral"},"bb_width":{"value":9.14,"signal":"Squeeze"},"bb_pctb":{"value":0.065,"signal":"Sell"},"keltner_upper":{"value":80.5,"signal":"Neutral"},"keltner_lower":{"value":71.94,"signal":"Neutral"},"donchian_high":{"value":80.54,"signal":"Neutral"},"donchian_low":{"value":70.84,"signal":"Neutral"},"hv_20":{"value":39.7,"signal":"Normal"},"stddev_20":{"value":1.71,"signal":"Low"},"chaikin_vol":{"value":-12.0,"signal":"Falling"},"mass_index":{"value":25.0,"signal":"Normal"},"ulcer_index":{"value":3.68,"signal":"Normal"}},"volume":{"volume":{"value":313601,"signal":"Normal"},"obv":{"value":9167211,"signal":"Sell"},"ad_line":{"value":9082078,"signal":"Sell"},"cmf_20":{"value":-0.203,"signal":"Sell"},"mfi_14":{"value":41.3,"signal":"Neutral"},"vpt":{"value":29699,"signal":"Sell"},"force_index":{"value":-121222.0,"signal":"Sell"},"vol_osc":{"value":-20.0,"signal":"Sell"},"nvi":{"value":985.0,"signal":"Sell"},"pvi":{"value":2723.1,"signal":"Buy"}},"pattern":{"close_position":{"value":90.8,"signal":"Buy"},"body_ratio":{"value":46.2,"signal":"Normal"},"upper_shadow":{"value":9.2,"signal":"Neutral"},"lower_shadow":{"value":44.6,"signal":"Neutral"},"gap_pct":{"value":0.11,"signal":"Neutral"},"intraday_range":{"value":1.82,"signal":"Normal"},"doji":{"value":"False","signal":"Neutral"},"engulfing":{"value":"None","signal":"Neutral"},"hammer":{"value":"False","signal":"Neutral"},"inside_bar":{"value":"False","signal":"Neutral"},"outside_bar":{"value":"False","signal":"Neutral"},"morning_star":{"value":"False","signal":"Neutral"},"evening_star":{"value":"False","signal":"Neutral"},"pattern_name":{"value":"None","signal":"Neutral"},"double_top":{"value":true,"signal":"Sell"},"chart_pattern":{"value":"雙頂 Double Top","signal":"Sell"},"head_shoulders":{"value":false,"signal":"Neutral"},"inv_head_shoulders":{"value":false,"signal":"Neutral"},"double_bottom":{"value":false,"signal":"Neutral"},"sym_triangle":{"value":false,"signal":"Neutral"},"asc_triangle":{"value":false,"signal":"Neutral"},"desc_triangle":{"value":false,"signal":"Neutral"},"rising_wedge":{"value":false,"signal":"Neutral"},"falling_wedge":{"value":false,"signal":"Neutral"},"bull_flag":{"value":false,"signal":"Neutral"},"bear_flag":{"value":false,"signal":"Neutral"},"cup_handle":{"value":false,"signal":"Neutral"}},"support_resistance":{"pivot":{"value":71.67,"signal":"Buy"},"r1":{"value":72.49,"signal":"Near"},"s1":{"value":71.19,"signal":"Neutral"},"r2":{"value":72.97,"signal":"Neutral"},"s2":{"value":70.37,"signal":"Neutral"},"r3":{"value":73.79,"signal":"Neutral"},"s3":{"value":69.89,"signal":"Neutral"},"high_52wk":{"value":114.52,"signal":"Neutral"},"low_52wk":{"value":70.84,"signal":"Near"},"ath":{"value":114.52,"signal":"Neutral"},"ath_dist":{"value":62.9,"signal":"Far"},"fib_0":{"value":70.84,"signal":"Support"},"fib_236":{"value":76.22,"signal":"Resistance"},"fib_382":{"value":79.54,"signal":"Resistance"},"fib_500":{"value":82.23,"signal":"Resistance"},"fib_618":{"value":84.92,"signal":"Resistance"},"fib_786":{"value":88.75,"signal":"Resistance"},"fib_100":{"value":93.62,"signal":"Resistance"},"vpoc":{"value":76.99,"signal":"Resistance"}},"relative":{"rs_line":{"value":0.0976,"signal":"Sell"},"rs_line_trend":{"value":"Falling","signal":"Sell"},"beta_60":{"value":0.86,"signal":"Normal"},"correlation_spy":{"value":0.37,"signal":"Normal"},"alpha_60":{"value":-107.8,"signal":"Sell"},"info_ratio":{"value":-3.29,"signal":"Sell"}},"statistical":{"sharpe_60":{"value":-2.05,"signal":"Sell"},"sortino_60":{"value":-1.71,"signal":"Sell"},"mdd_60":{"value":-22.5,"signal":"High Risk"},"skewness":{"value":-1.04,"signal":"Sell"},"kurtosis":{"value":3.55,"signal":"High Risk"},"var_95":{"value":-3.56,"signal":"Normal"},"cvar_95":{"value":-7.22,"signal":"High Risk"}},"time_based":{"consec_up":{"value":1,"signal":"Neutral"},"consec_down":{"value":0,"signal":"Neutral"},"day_of_week":{"value":"Thu","signal":"Neutral"},"days_since_high":{"value":133,"signal":"Sell"}}},"validation":{"checks":123,"passed":123,"errors":0,"warnings":1,"status":"PASS","error_list":[],"warning_list":["chart_pattern '雙頂 Double Top (M 頭)': Sell but target $82.96 > current $72.02"],"indicator_count":103,"empty_signals":0}}