{"symbol":"THRO","date":"2026-04-15","bars_available":1026,"tradingview_rating":{"summary":{"signal":"Strong Buy","score":0.62,"buy":18,"sell":2,"neutral":6},"oscillators":{"signal":"Neutral","score":0.09,"buy":3,"sell":2,"neutral":6,"details":{"RSI(14)":{"value":74.8,"signal":0},"Stoch(14,3,3)":{"value":null,"signal":0},"CCI(20)":{"value":168.7,"signal":-1},"ADX(14)":{"value":null,"signal":0},"AO":{"value":1.08,"signal":1},"Momentum(10)":{"value":3.43,"signal":1},"MACD(12,26,9)":{"value":null,"signal":0},"StochRSI(3,3,14,14)":{"value":null,"signal":0},"W%R(14)":{"value":-0.7,"signal":-1},"BBP(13)":{"value":2.58,"signal":1},"UO(7,14,28)":{"value":79.5,"signal":0}}},"moving_averages":{"signal":"Strong Buy","score":1.0,"buy":15,"sell":0,"neutral":0,"details":{"SMA(10)":{"value":37.78,"signal":1},"SMA(20)":{"value":37.31,"signal":1},"SMA(30)":{"value":37.49,"signal":1},"SMA(50)":{"value":37.95,"signal":1},"SMA(100)":{"value":38.24,"signal":1},"SMA(200)":{"value":37.51,"signal":1},"EMA(10)":{"value":38.17,"signal":1},"EMA(20)":{"value":37.78,"signal":1},"EMA(30)":{"value":37.75,"signal":1},"EMA(50)":{"value":37.85,"signal":1},"EMA(100)":{"value":37.87,"signal":1},"EMA(200)":{"value":37.13,"signal":1},"HMA(9)":{"value":39.45,"signal":1},"VWMA(20)":{"value":37.17,"signal":1},"Ichimoku(9,26,52)":{"value":37.55,"signal":1}}}},"extended_rating":{"summary":{"signal":"Buy","score":0.39,"buy":47,"sell":7,"neutral":49},"categories":{"trend":{"signal":"Strong Buy","score":0.78,"buy":7,"sell":0,"neutral":2},"momentum":{"signal":"Buy","score":0.2,"buy":3,"sell":2,"neutral":0},"volatility":{"signal":"Buy","score":0.25,"buy":7,"sell":3,"neutral":6},"volume":{"signal":"Buy","score":0.5,"buy":6,"sell":1,"neutral":3},"pattern":{"signal":"Neutral","score":0.07,"buy":2,"sell":0,"neutral":25},"support_resistance":{"signal":"Strong Buy","score":0.79,"buy":15,"sell":0,"neutral":4},"relative":{"signal":"Buy","score":0.5,"buy":4,"sell":1,"neutral":1},"statistical":{"signal":"Buy","score":0.14,"buy":1,"sell":0,"neutral":6},"time_based":{"signal":"Buy","score":0.5,"buy":2,"sell":0,"neutral":2}}},"chart_patterns":[{"name":"盤整震盪","type":"trend","direction":"Neutral","reliability":"趨勢判定 (20日 +5.9%, 50日 +3.0%)","description":"近 20 日漲跌 +5.9%，均線糾結，無明確方向。價格在 MA20 ($37.31) 和 MA50 ($37.95) 之間來回。","current_status":"收盤 $39.41 | MA20 $37.31 | MA50 $37.95 | 均線糾結","price_target":null,"target_logic":"上方壓力 MA20 = $37.31，下方支撐 MA50 = $37.95","prediction":"等待方向。突破 MA20 ($37.31) 看多，跌破 MA50 ($37.95) 看空。量能放大時關注突破方向。","key_levels":{"ma20":37.31,"ma50":37.95,"current":39.41}}],"indicators":{"trend":{"parabolic_sar":{"value":36.23,"signal":"Buy"},"supertrend":{"value":37.46,"signal":"Buy"},"aroon_up":{"value":100.0,"signal":"Buy"},"aroon_down":{"value":64.0,"signal":"Neutral"},"aroon_osc":{"value":36.0,"signal":"Buy"},"vortex_plus":{"value":1.12,"signal":"Buy"},"vortex_minus":{"value":0.679,"signal":"Buy"},"lr_slope":{"value":0.105,"signal":"Buy"},"r_squared":{"value":0.349,"signal":"Normal"}},"momentum":{"roc_14":{"value":8.45,"signal":"Buy"},"tsi":{"value":0.0,"signal":"Sell"},"coppock":{"value":7.69,"signal":"Buy"},"ppo":{"value":0.77,"signal":"Buy"},"dpo":{"value":-1.33,"signal":"Sell"}},"volatility":{"atr_14":{"value":0.6,"signal":"Low"},"atr_pct":{"value":1.51,"signal":"Low"},"bb_upper":{"value":39.36,"signal":"Sell"},"bb_middle":{"value":37.31,"signal":"Buy"},"bb_lower":{"value":35.26,"signal":"Neutral"},"bb_width":{"value":10.99,"signal":"Normal"},"bb_pctb":{"value":1.012,"signal":"Buy"},"keltner_upper":{"value":38.98,"signal":"Sell"},"keltner_lower":{"value":36.58,"signal":"Neutral"},"donchian_high":{"value":39.44,"signal":"Buy"},"donchian_low":{"value":35.31,"signal":"Neutral"},"hv_20":{"value":22.0,"signal":"Normal"},"stddev_20":{"value":1.03,"signal":"Low"},"chaikin_vol":{"value":-9.8,"signal":"Falling"},"mass_index":{"value":25.0,"signal":"Normal"},"ulcer_index":{"value":1.14,"signal":"Low Risk"}},"volume":{"volume":{"value":680531,"signal":"Normal"},"obv":{"value":-102927245,"signal":"Buy"},"ad_line":{"value":15259423,"signal":"Buy"},"cmf_20":{"value":0.012,"signal":"Neutral"},"mfi_14":{"value":68.0,"signal":"Neutral"},"vpt":{"value":-570344,"signal":"Buy"},"force_index":{"value":226648.0,"signal":"Buy"},"vol_osc":{"value":-30.1,"signal":"Sell"},"nvi":{"value":1771.0,"signal":"Buy"},"pvi":{"value":915.0,"signal":"Buy"}},"pattern":{"close_position":{"value":91.2,"signal":"Buy"},"body_ratio":{"value":61.8,"signal":"Normal"},"upper_shadow":{"value":8.8,"signal":"Neutral"},"lower_shadow":{"value":29.4,"signal":"Neutral"},"gap_pct":{"value":0.1,"signal":"Neutral"},"intraday_range":{"value":0.87,"signal":"Low"},"doji":{"value":"False","signal":"Neutral"},"engulfing":{"value":"None","signal":"Neutral"},"hammer":{"value":"False","signal":"Neutral"},"inside_bar":{"value":"False","signal":"Neutral"},"outside_bar":{"value":"False","signal":"Neutral"},"morning_star":{"value":"False","signal":"Neutral"},"evening_star":{"value":"False","signal":"Neutral"},"pattern_name":{"value":"None","signal":"Neutral"},"chart_pattern":{"value":"盤整震盪","signal":"Neutral"},"head_shoulders":{"value":false,"signal":"Neutral"},"inv_head_shoulders":{"value":false,"signal":"Neutral"},"double_top":{"value":false,"signal":"Neutral"},"double_bottom":{"value":false,"signal":"Neutral"},"sym_triangle":{"value":false,"signal":"Neutral"},"asc_triangle":{"value":false,"signal":"Neutral"},"desc_triangle":{"value":false,"signal":"Neutral"},"rising_wedge":{"value":false,"signal":"Neutral"},"falling_wedge":{"value":false,"signal":"Neutral"},"bull_flag":{"value":false,"signal":"Neutral"},"bear_flag":{"value":false,"signal":"Neutral"},"cup_handle":{"value":false,"signal":"Neutral"}},"support_resistance":{"pivot":{"value":39.32,"signal":"Buy"},"r1":{"value":39.53,"signal":"Near"},"s1":{"value":39.19,"signal":"Near"},"r2":{"value":39.66,"signal":"Near"},"s2":{"value":38.98,"signal":"Neutral"},"r3":{"value":39.87,"signal":"Neutral"},"s3":{"value":38.85,"signal":"Neutral"},"high_52wk":{"value":39.44,"signal":"Near"},"low_52wk":{"value":27.78,"signal":"Neutral"},"ath":{"value":39.44,"signal":"Near ATH"},"ath_dist":{"value":99.9,"signal":"Near ATH"},"fib_0":{"value":35.31,"signal":"Support"},"fib_236":{"value":36.28,"signal":"Support"},"fib_382":{"value":36.89,"signal":"Support"},"fib_500":{"value":37.37,"signal":"Support"},"fib_618":{"value":37.86,"signal":"Support"},"fib_786":{"value":38.56,"signal":"Support"},"fib_100":{"value":39.44,"signal":"Near"},"vpoc":{"value":36.78,"signal":"Support"}},"relative":{"rs_line":{"value":0.0567,"signal":"Sell"},"rs_line_trend":{"value":"Rising","signal":"Buy"},"beta_60":{"value":0.11,"signal":"Low"},"correlation_spy":{"value":0.1,"signal":"Low"},"alpha_60":{"value":6.2,"signal":"Buy"},"info_ratio":{"value":0.11,"signal":"Neutral"}},"statistical":{"sharpe_60":{"value":0.38,"signal":"Neutral"},"sortino_60":{"value":0.39,"signal":"Neutral"},"mdd_60":{"value":-10.2,"signal":"Normal"},"skewness":{"value":0.39,"signal":"Neutral"},"kurtosis":{"value":1.19,"signal":"Normal"},"var_95":{"value":-1.74,"signal":"Low Risk"},"cvar_95":{"value":-2.19,"signal":"Normal"}},"time_based":{"consec_up":{"value":3,"signal":"Buy"},"consec_down":{"value":0,"signal":"Neutral"},"day_of_week":{"value":"Wed","signal":"Neutral"},"days_since_high":{"value":0,"signal":"Buy"}}},"validation":{"checks":122,"passed":122,"errors":0,"warnings":0,"status":"PASS","error_list":[],"warning_list":[],"indicator_count":103,"empty_signals":0}}